solvice_vrp_solver/__init__.py
solvice_vrp_solver/_base_client.py
solvice_vrp_solver/_client.py
solvice_vrp_solver/_compat.py
solvice_vrp_solver/_constants.py
solvice_vrp_solver/_exceptions.py
solvice_vrp_solver/_files.py
solvice_vrp_solver/_models.py
solvice_vrp_solver/_qs.py
solvice_vrp_solver/_resource.py
solvice_vrp_solver/_response.py
solvice_vrp_solver/_streaming.py
solvice_vrp_solver/_types.py
solvice_vrp_solver/_version.py
solvice_vrp_solver/py.typed
solvice_vrp_solver/_utils/__init__.py
solvice_vrp_solver/_utils/_compat.py
solvice_vrp_solver/_utils/_datetime_parse.py
solvice_vrp_solver/_utils/_logs.py
solvice_vrp_solver/_utils/_proxy.py
solvice_vrp_solver/_utils/_reflection.py
solvice_vrp_solver/_utils/_resources_proxy.py
solvice_vrp_solver/_utils/_streams.py
solvice_vrp_solver/_utils/_sync.py
solvice_vrp_solver/_utils/_transform.py
solvice_vrp_solver/_utils/_typing.py
solvice_vrp_solver/_utils/_utils.py
solvice_vrp_solver/lib/.keep
solvice_vrp_solver/resources/__init__.py
solvice_vrp_solver/resources/vrp/__init__.py
solvice_vrp_solver/resources/vrp/jobs.py
solvice_vrp_solver/resources/vrp/vrp.py
solvice_vrp_solver/types/__init__.py
solvice_vrp_solver/types/custom_distance_matrices.py
solvice_vrp_solver/types/custom_distance_matrices_param.py
solvice_vrp_solver/types/explanation_options.py
solvice_vrp_solver/types/explanation_options_param.py
solvice_vrp_solver/types/job.py
solvice_vrp_solver/types/job_param.py
solvice_vrp_solver/types/location.py
solvice_vrp_solver/types/location_param.py
solvice_vrp_solver/types/message.py
solvice_vrp_solver/types/options.py
solvice_vrp_solver/types/options_param.py
solvice_vrp_solver/types/period.py
solvice_vrp_solver/types/period_param.py
solvice_vrp_solver/types/relation.py
solvice_vrp_solver/types/relation_param.py
solvice_vrp_solver/types/relation_type.py
solvice_vrp_solver/types/request.py
solvice_vrp_solver/types/resource.py
solvice_vrp_solver/types/resource_param.py
solvice_vrp_solver/types/rule.py
solvice_vrp_solver-0.1.0a5.dist-info/METADATA
solvice_vrp_solver-0.1.0a5.dist-info/WHEEL
solvice_vrp_solver-0.1.0a5.dist-info/licenses/LICENSE
solvice_vrp_solver-0.1.0a5.dist-info/RECORD
